Workbook

Sheet Template
A1: Heading
B2: Sub Heading | G2: Separation Column
C3: Sub Heading
B4: Width 0.75
D5: Particulars | E5: Constant | F5: Units | H5: Calulations->
B7: 0.0075 | D7: Width 40 | E7: 12 | F7: 12

Sheet Historical
A1: Britannia Industries Limited
A2: Historical Financial Information
H3: 2020 | I3: =H3+1 -> 2021 | J3: =I3+1 -> 2022 | K3: =J3+1 -> 2023 | L3: =K3+1 -> 2024 | M3: =L3+1 -> 2025
A4: Income Satement
D6: Revenue from operations | H6: 11443.99 | I6: 12883.04 | J6: 13944.67 | K6: 15984.9 | L6: 16546.21 | M6: 17535.02
D7: Other operating revenues | H7: 155.56 | I7: 253.1 | J7: 191.59 | K7: 315.65 | L7: 223.06 | M7: 407.65
D8: Total Revenue from operations | H8: 11599.55 | I8: 13136.14 | J8: 14136.26 | K8: 16300.55 | L8: 16769.27 | M8: 17942.67
D9: Other income | H9: 279.4 | I9: 312.87 | J9: 222.83 | K9: 215.86 | L9: 214.18 | M9: 227.09
D10: Total Income | H10: 11878.95 | I10: 13449.01 | J10: 14359.09 | K10: 16516.41 | L10: 16983.45 | M10: 18169.76
D11: Cost of materials consumed | H11: 5684.98 | I11: 6502.33 | J11: 7473.97 | K11: 8326.7 | L11: 8546.89 | M11: 9859.45
D12: Purchases of stock-in-trade | H12: 1189.92 | I12: 1160.89 | J12: 1361.59 | K12: 1337.13 | L12: 941.48 | M12: 809.35
D13: Changes in inventories of finished goods, work-in-progress and stock-in-trade | H13: 52.57 | I13: -37.12 | J13: -75.26 | K13: -72.53 | L13: 3.66 | M13: -64.75
D14: Employee benefits expense | H14: 486.69 | I14: 527.38 | J14: 542.26 | K14: 658.38 | L14: 708.7 | M14: 704.59
D15: Finance costs | H15: 76.9 | I15: 110.9 | J15: 144.29 | K15: 169.1 | L15: 164 | M15: 138.8
D16: Depreciation and amortisation expense | H16: 184.81 | I16: 197.85 | J16: 200.54 | K16: 225.96 | L16: 300.7 | M16: 313.34
D17: Other expenses | H17: 2342.21 | I17: 2473.37 | J17: 2632.31 | K17: 3219.91 | L17: 3398.46 | M17: 3446.88
... D27: Profit for the year | H27: 1393.6 | I27: 1850.59 | J27: 1515.98 | K27: 2316.32 | L27: 2134.22 | M27: 2177.86
A29: Balancesheet | H29: 2020 | I29: =H29+1 -> 2021 | J29: =I29+1 -> 2022 | K29: =J29+1 -> 2023 | L29: =K29+1 -> 2024 | M29: =L29+1 -> 2025
D30: Particulars
D31: ASSETS | X31: 2020 | Y31: 2021 | Z31: 2022 | AA31: 2023 | AB31: 2024 | AC31: 2025
D32: Non-current assets
D33: Property, plant and equipment | H33: 1716.37 | I33: 1634.3 | J33: 1584.05 | K33: 2472.19 | L33: 2602.94 | M33: 2734.61
D34: Capital work-in-progress | H34: 39.55 | I34: 116.52 | J34: 535.68 | K34: 105.08 | L34: 187.54 | M34: 89.2
D35: Investment property | H35: 14.47 | I35: 14.21 | J35: 13.95 | K35: 40.63 | L35: 27.48 | M35: 28.9
D36: Goodwill | H36: 138.97 | I36: 135.9 | J36: 139.61 | K36: 128.16 | L36: 129.82 | M36: 132.78
D37: Other intangible assets | H37: 8.37 | I37: 8.54 | J37: 15.6 | K37: 14.24 | L37: 10.9 | M37: 7.51
D38: Investment in associates and joint venture | H38: 1.48 | I38: 2.29 | J38: 2.09 | K38: 495.16 | L38: 494.36 | M38: 483.62
D39: Financial assets (Non-current):
D40: (i) Investments | H40: 1882.98 | I40: 1385.15 | J40: 926.55 | K40: 1028.09 | L40: 575.85 | M40: 1270.17
D41: (ii) Loans receivable | H41: 202.95 | I41: 74.58 | J41: 100 | K41: 150 | L41: 0 | M41: 25
D42: (iii) Other financial assets | H42: 31.33 | I42: 30.13 | J42: 31.8 | K42: 23.57 | L42: 25.5 | M42: 28.19
D43: Deferred tax assets (net) | H43: 19.56 | I43: 9.66 | J43: 51.67 | K43: 57.25 | L43: 43.88 | M43: 36.65
D44: Income-tax assets (net) | H44: 68.77 | I44: 71.84 | J44: 44.93 | K44: 43.64 | L44: 67.95 | M44: 46.26
D45: Other non-current assets | H45: 42.46 | I45: 105.98 | J45: 99.18 | K45: 48.56 | L45: 58.68 | M45: 42.04
D46: Total non-current assets | H46: 4167.26 | I46: 3589.1 | J46: 3545.11 | K46: 4564.57 | L46: 4224.9 | M46: 4924.87
D47: Current assets
D48: Inventories | H48: 740.96 | I48: 1091.49 | J48: 1367.49 | K48: 1193.18 | L48: 1181.22 | M48: 1236.51
D49: Financial assets (Current):
D50: (i) Investments | H50: 1008.77 | I50: 1393.25 | J50: 833.73 | K50: 1800.99 | L50: 1696.51 | M50: 1111.64
D51: (ii) Trade receivables | H51: 320.36 | I51: 257.27 | J51: 331.93 | K51: 328.94 | L51: 393.33 | M51: 448.61
D52: (iii) Cash and cash equivalents | H52: 81.23 | I52: 142.74 | J52: 117.99 | K52: 102.38 | L52: 322.8 | M52: 132.72
D53: (iv) Bank balances other than (iii) above | H53: 41.62 | I53: 68.6 | J53: 66.91 | K53: 95.6 | L53: 123.55 | M53: 179.7
D54: (v) Loans receivable | H54: 1110.11 | I54: 946.56 | J54: 698 | K54: 560 | L54: 460 | M54: 50
D55: (vi) Other financial assets | H55: 229.75 | I55: 397.76 | J55: 428.03 | K55: 451.96 | L55: 531.13 | M55: 630.46
D56: Other current assets | H56: 142.17 | I56: 122.01 | J56: 138.22 | K56: 180.74 | L56: 133.71 | M56: 123.98
D57: Assets held-for-sale | H57: 0 | I57: 0 | J57: 0 | K57: 32.36 | L57: 6.41 | M57: 0
D58: Total current assets | H58: 3674.97 | I58: 4419.68 | J58: 3982.3 | K58: 4746.23 | L58: 4848.66 | M58: 3913.68
D59: Total assets | H59: 7842.23 | I59: 8008.78 | J59: 7527.41 | K59: 9352.72 | L59: 9073.56 | M59: 8838.55
D60: EQUITY AND LIABILITIES
D61: Equity
D62: Equity share capital | H62: 24.05 | I62: 24.09 | J62: 24.09 | K62: 24.09 | L62: 24.09 | M62: 24.09
D63: Other equity | H63: 4378.78 | I63: 3523.57 | J63: 2534.01 | K63: 3510.18 | L63: 3917.43 | M63: 4331.63
D64: Equity attributable to owners | H64: 4402.83 | I64: 3547.66 | J64: 2558.1 | K64: 3534.27 | L64: 3941.52 | M64: 4355.72
D65: Non-controlling interests | H65: 35.65 | I65: 36.34 | J65: 27.5 | K65: 30.23 | L65: 24.5 | M65: 25.6
D66: Total equity | H66: 4438.48 | I66: 3584 | J66: 2585.6 | K66: 3564.5 | L66: 3966.02 | M66: 4381.32
D67: Liabilities
D68: Non-current liabilities
D69: Financial liabilities (Non-current):
D70: (i) Borrowings | H70: 766.06 | I70: 747.75 | J70: 706.99 | K70: 1551.8 | L70: 904.72 | M70: 712.94
D71: (ii) Lease liabilities | H71: 0 | I71: 0 | J71: 13.76 | K71: 14.36 | L71: 20.13 | M71: 19.45
D72: (iii) Other financial liabilities | H72: 46.54 | I72: 54.07 | J72: 52.64 | K72: 60.15 | L72: 65.66 | M72: 72.21
D73: Deferred tax liabilities (net) | H73: 12.69 | I73: 8.69 | J73: 0.81 | K73: 1.87 | L73: 2.06 | M73: 1.8
D74: Provisions (Non-current) | H74: 0 | I74: 0 | J74: 20.47 | K74: 25.64 | L74: 30.56 | M74: 32.57
D75: Total non-current liabilities | H75: 825.29 | I75: 810.51 | J75: 794.67 | K75: 1651.95 | L75: 1023.13 | M75: 838.97
D76: Current liabilities
D77: Financial liabilities (Current):
D78: (i) Borrowings | H78: 747.99 | I78: 1339.42 | J78: 1758.55 | K78: 1428.71 | L78: 1136.49 | M78: 511.83
D79: (ii) Lease liabilities | H79: 0 | I79: 0 | J79: 1.9 | K79: 2.5 | L79: 3.62 | M79: 2.29
D80: (iii) Trade payables:
D81: (a) dues of micro and small enterprises | H81: 8.53 | I81: 28.44 | J81: 62.76 | K81: 43.92 | L81: 30.83 | M81: 27.83
D82: (b) dues of other than micro and small enterprises | H82: 1038.47 | I82: 1286.31 | J82: 1260.05 | K82: 1404.89 | L82: 1596.65 | M82: 1724.4
D83: (iv) Other financial liabilities | H83: 311.91 | I83: 356.01 | J83: 393.96 | K83: 496.21 | L83: 497.4 | M83: 429.34
D84: Other current liabilities | H84: 150.08 | I84: 140.54 | J84: 130.73 | K84: 176.34 | L84: 167.29 | M84: 194.7
D85: Provisions (Current) | H85: 273.7 | I85: 387.47 | J85: 464.64 | K85: 513.39 | L85: 559.2 | M85: 604.66
D86: Current tax liabilities (net) | H86: 47.78 | I86: 76.08 | J86: 74.55 | K86: 68.44 | L86: 92.93 | M86: 123.21
D87: Total current liabilities | H87: 2578.46 | I87: 3614.27 | J87: 4147.14 | K87: 4134.4 | L87: 4084.41 | M87: 3618.26
D88: Total liabilities | H88: 3403.75 | I88: 4424.78 | J88: 4941.81 | K88: 5788.22 | L88: 5107.54 | M88: 4457.23
D89: Total equity and liabilities | H89: 7842.23 | I89: 8008.78 | J89: 7527.41 | K89: 9352.72 | L89: 9073.56 | M89: 8838.55
A91: Cashflow Statement | H91: 2020 | I91: =H91+1 -> 2021 | J91: =I91+1 -> 2022 | K91: =J91+1 -> 2023 | L91: =K91+1 -> 2024 | M91: =L91+1 -> 2025
D92: Particulars (₹ in Crores)
D93: A. CASH FLOWS FROM OPERATING ACTIVITIES
D94: Profit before tax and share of profits/(loss) of associates and JV (after exceptional items) | H94: 1843.86 | I94: 2512.8 | J94: 2078.53 | K94: 3027.36 | L94: 2916.66 | M94: 2937.31
D95: Depreciation and amortisation expense | H95: 184.81 | I95: 197.85 | J95: 200.54 | K95: 225.91 | L95: 300.46 | M95: 313.34
D96: Share based payment (ESOP) expense | H96: 21.58 | I96: 18.94 | J96: 4.78
D97: Net gain on financial assets at fair value through P&L | H97: -89.88 | I97: -65.47 | J97: -28.91 | K97: -42.08 | L97: -25.17 | M97: -81.35
D98: (Profit)/Loss on sale of PPE | H98: -0.11 | I98: -0.33 | J98: -0.95 | K98: -0.83 | L98: -0.45 | M98: -1.24
D99: Profit on sale of investments (incl. fair valuation gain) | J99: 0 | K99: -375.6
D100: Interest income from financial assets at amortised cost | H100: -176.77 | I100: -234.66 | J100: -184.6 | K100: -163.15 | L100: -178.75 | M100: -132.8
D101: Finance costs | H101: 76.9 | I101: 110.9 | J101: 144.29 | K101: =169.1+5.59 -> 174.69 | L101: 164 | M101: 138.8
D102: Changes in Inventories | H102: 42.99 | I102: -351.44 | J102: -274.76 | K102: 177.15 | L102: 12.6 | M102: -54.33
D103: Changes in Trade receivables | H103: 78.85 | I103: 61.4 | J103: -72.21 | K103: 1.29 | L103: -63.65 | M103: -53.44
D104: Changes in Loans receivable, other fin. assets, bank balances & other assets | H104: -23.66 | I104: -170.82
D105: Changes in Other financial assets and other assets | J105: -44.29 | K105: -64.82 | L105: -24.52 | M105: -106.58
D106: Changes in Trade payables, other fin. liabilities, other liabilities & provisions | H106: 29.21 | I106: 404.71 | J106: 64.01 | K106: 292.04 | L106: 236.67 | M106: 210.15
D107: Cash generated from operating activities | H107: 1987.78 | I107: 2483.88 | J107: 1886.43 | K107: 3251.96 | L107: 3337.85 | M107: 3169.86
D108: Income-tax paid, net of refund | H108: -503.25 | I108: -632.81 | J108: -586.91 | K108: -725.75 | L108: -764.87 | M108: -689.21
D109: Net cash generated from operating activities (A) | H109: 1484.53 | I109: 1851.07 | J109: 1299.52 | K109: 2526.21 | L109: 2572.98 | M109: 2480.65
D110: B. CASH FLOWS FROM INVESTING ACTIVITIES
D111: Acquisition of PPE and other intangible assets | H111: -244.17 | I111: -242.07 | J111: -550.18 | K111: -711.46 | L111: -552.87 | M111: -374.85
D112: Proceeds from sale of PPE | H112: 0.73 | I112: 2.17 | J112: 0 | K112: 0 | L112: 64.52 | M112: 4.58
...

Sheet Model
A1: Britannia Industries Limited | H1: Historical Period | N1: Forcasted Period
A2: Financial Statement and Analysis | F2: Units | H2: 2020 | I2: =H2+1 -> 2021 | J2: =I2+1 -> 2022 | K2: =J2+1 -> 2023 | L2: =K2+1 -> 2024 | M2: =L2+1 -> 2025 | N2: =M2+1 -> 2026 | O2: =N2+1 -> 2027 | P2: =O2+1 -> 2028 | ... S2: =R2+1 -> 2031
A4: Ratios & Assumptions
D6: Live Scenario | E6: Base Case | F6: Units
D7: Revenue(Growth) | F7: % | I7: =I26/H26-1 -> 0.13246979 | J7: =J26/I26-1 -> 0.076134999 | K7: =K26/J26-1 -> 0.15310202 | L7: =L26/K26-1 -> 0.028754858 | M7: =M26/L26-1 -> 0.069973231 | N7: {=_xlfn.XLOOKUP(E6,'Scenario Analysis'!D5:D7,'Scenario Analysis'!H5:M7)} -> 0.092086981 | O7: 0.082878283 | P7: 0.074590454 | Q7: 0.067131409 | R7: 0.060418268 | S7: 0.054376441
D8: Cost of Goood Sold (% of Revenue) | F8: % | H8: =-H27/H26 -> 0.59721886 | I8: =-I27/I26 -> 0.58054345 | J8: =-J27/J26 -> 0.61970422 | K8: =-K27/K26 -> 0.58840346 | L8: =-L27/L26 -> 0.56603716 | M8: =-M27/M26 -> 0.59099621 | N8: =AVERAGE(H8:M8) -> 0.59048389 | O8: =N8 -> 0.59048389 | P8: =O8 -> 0.59048389 | Q8: =P8 -> 0.59048389 | R8: =Q8 -> 0.59048389 | S8: =R8 -> 0.59048389
D9: Salaries and Benefits (% of Revenue) | F9: % | H9: =-H30/H26 -> 0.041957662 | I9: =-I30/I26 -> 0.040147258 | J9: =-J30/J26 -> 0.03835951 | K9: =-K30/K26 -> 0.040390048 | L9: =-L30/L26 -> 0.042261828 | M9: =-M30/M26 -> 0.039268961 | N9: =AVERAGE(H9:M9) -> 0.040397544 | O9: =N9 -> 0.040397544 | P9: =O9 -> 0.040397544 | Q9: =P9 -> 0.040397544 | R9: =Q9 -> 0.040397544 | S9: =R9 -> 0.040397544
D10: Other SG&A Expenses (% of Revenue) | F10: % | H10: =-H31/H26 -> 0.20192249 | I10: =-I31/I26 -> 0.18828743 | J10: =-J31/J26 -> 0.18620979 | K10: =-K31/K26 -> 0.19753383 | L10: =-L31/L26 -> 0.20265998 | M10: =-M31/M26 -> 0.19210519 | N10: =AVERAGE(H10:M10) -> 0.19478645 | O10: =N10 -> 0.19478645 | P10: =O10 -> 0.19478645 | Q10: =P10 -> 0.19478645 | R10: =Q10 -> 0.19478645 | S10: =R10 -> 0.19478645
D11: Depreciation and amortisation expense (% of PP&E) | F11: % | I11: =-I33/H56 -> 0.11122917 | J11: =-J33/I56 -> 0.11307138 | K11: =-K33/J56 -> 0.10513288 | L11: =-L33/K56 -> 0.11424164 | M11: =-M33/L56 -> 0.11076547 | N11: =AVERAGE(H11:M11) -> 0.11088811 | O11: =N11 -> 0.11088811 | P11: =O11 -> 0.11088811 | Q11: =P11 -> 0.11088811 | R11: =Q11 -> 0.11088811 | S11: =R11 -> 0.11088811
D12: Interest Expenses (% of Debt) | F12: % | I12: =-I35/H68 -> 0.073247251 | J12: =-J35/I68 -> 0.069131887 | K12: =-K35/J68 -> 0.068152507 | L12: =-L35/K68 -> 0.054714633 | M12: =-M35/L68 -> 0.067216798 | N12: =AVERAGE(H12:M12) -> 0.066492615 | O12: =N12 -> 0.066492615 | P12: =O12 -> 0.066492615 | Q12: =P12 -> 0.066492615 | R12: =Q12 -> 0.066492615 | S12: =R12 -> 0.066492615
D13: Other Income(Expenses) (% of Revenue) | F13: % | H13: =H39/H26 -> 0.024087141 | I13: =I39/I26 -> 0.023817499 | J13: =J39/J26 -> 0.015763009 | K13: =K39/K26 -> 0.013242498 | L13: =L39/L26 -> 0.012772172 | M13: =M39/M26 -> 0.012656422 | N13: =AVERAGE(H13:M13) -> 0.017056457 | O13: =N13 -> 0.017056457 | P13: =O13 -> 0.017056457 | Q13: =P13 -> 0.017056457 | R13: =Q13 -> 0.017056457 | S13: =R13 -> 0.017056457
D14: Taxes (% of Earnings before Tax) | F14: % | H14: =-H41/H40 -> 0.24437456 | I14: =-I41/I40 -> 0.26377203 | J14: =-J41/J40 -> 0.27059344 | K14: =-K41/K40 -> 0.23623618 | L14: =-L41/L40 -> 0.26746457 | M14: =-M41/M40 -> 0.25583191 | N14: =AVERAGE(H14:M14) -> 0.25637878 | O14: =N14 -> 0.25637878 | P14: =O14 -> 0.25637878 | Q14: =P14 -> 0.25637878 | R14: =Q14 -> 0.25637878 | S14: =R14 -> 0.25637878
D15: Dividend Payout | F15: % | H15: =-H101/H42 -> 0.31036883 | I15: =-I101/I42 -> 1.5258647 | J15: =-J101/J42 -> 1.6392543 | K15: =-K101/K42 -> 0.58681011 | L15: =-L101/L42 -> 0.81175793 | M15: =-M101/M42 -> 0.81159487 | N15: =AVERAGE(K15:M15) -> 0.73672097 | O15: =N15 -> 0.73672097 | P15: =O15 -> 0.73672097 | Q15: =P15 -> 0.73672097 | R15: =Q15 -> 0.73672097 | S15: =R15 -> 0.73672097
D16: Accounts Recievables | F16: Days | H16: =H50/H26*365 -> 10.080684 | I16: =I50/I26*365 -> 7.1484888 | J16: =J50/J26*365 -> 8.5704741 | K16: =K50/K26*365 -> 7.3655858 | L16: =L50/L26*365 -> 8.5612224 | M16: =M50/M26*365 -> 9.1258798 | N16: =AVERAGE(H16:M16) -> 8.4753892 | O16: =N16 -> 8.4753892 | P16: =O16 -> 8.4753892 | Q16: =P16 -> 8.4753892 | R16: =Q16 -> 8.4753892 | S16: =R16 -> 8.4753892
D17: Inventory DIO | F17: Days | H17: =-H52/H27*365 -> 39.040285 | I17: =-I52/I27*365 -> 52.240837 | J17: =-J52/J27*365 -> 56.976799 | K17: =-K52/K27*365 -> 45.406848 | L17: =-L52/L27*365 -> 45.421822 | M17: =-M52/M27*365 -> 42.561677 | N17: =AVERAGE(H17:M17) -> 46.941378 | O17: =N17 -> 46.941378 | P17: =O17 -> 46.941378 | Q17: =P17 -> 46.941378 | R17: =Q17 -> 46.941378 | S17: =R17 -> 46.941378
D18: Accounts Payables DPO | F18: Days | H18: =-H65/H27*365 -> 55.165161 | I18: =-I65/I27*365 -> 79.965828 | J18: =-J65/J27*365 -> 71.529634 | K18: =-K65/K27*365 -> 74.01836 | L18: =-L65/L27*365 -> 81.708676 | M18: =-M65/M27*365 -> 75.091408 | N18: =AVERAGE(H18:M18) -> 72.913178 | O18: =N18 -> 72.913178 | P18: =O18 -> 72.913178 | Q18: =P18 -> 72.913178 | R18: =Q18 -> 72.913178 | S18: =R18 -> 72.913178
D19: Capital asset turnover ratio | F19: Times | H19: =H26/H56 -> 6.5211439 | I19: =I26/I56 -> 7.4066093 | J19: =J26/J56 -> 6.5772073 | K19: =K26/K56 -> 6.1928887 | L19: =L26/L56 -> 5.927925 | M19: =M26/M56 -> 6.2731783 | N19: =AVERAGE(H19:M19) -> 6.4831587 | O19: =N19 -> 6.4831587 | P19: =O19 -> 6.4831587 | Q19: =P19 -> 6.4831587 | R19: =Q19 -> 6.4831587 | S19: =R19 -> 6.4831587
D20: Investments as % of Earnings | F20: % | H20: =H53/H42 -> 0.72385907 | I20: =I53/I42 -> 0.752868 | J20: =J53/J42 -> 0.55000462 | K20: =K53/K42 -> 0.7775221 | L20: =L53/L42 -> 0.79490868 | M20: =M53/M42 -> 0.51042767 | N20: =AVERAGE(H20:M20) -> 0.68493169 | O20: =N20 -> 0.68493169 | P20: =O20 -> 0.68493169 | Q20: =P20 -> 0.68493169 | R20: =Q20 -> 0.68493169 | S20: =R20 -> 0.68493169
D21: Income Tax as % of Cashflow from operationns | F21: % | H21: =H87/-H86 -> 0.25317188 | I21: =I87/-I86 -> 0.25476674 | J21: =J87/-J86 -> 0.31112207 | K21: =K87/-K86 -> 0.2231731 | L21: =L87/-L86 -> 0.2291505 | M21: =M87/-M86 -> 0.21742601 | N21: =AVERAGE(H21:M21) -> 0.24813505 | O21: =N21 -> 0.24813505 | P21: =O21 -> 0.24813505 | Q21: =P21 -> 0.24813505 | R21: =Q21 -> 0.24813505 | S21: =R21 -> 0.24813505
A24: Income Statement | H24: 2020 | I24: =H24+1 -> 2021 | J24: =I24+1 -> 2022 | K24: =J24+1 -> 2023 | L24: =K24+1 -> 2024 | M24: =L24+1 -> 2025 | N24: =M24+1 -> 2026 | O24: =N24+1 -> 2027 | P24: =O24+1 -> 2028 | ... S24: =R24+1 -> 2031
B25: Income
D26: Revenue | F26: ₹ in Cr | H26: =Historical!H8 -> 11599.55 | I26: =Historical!I8 -> 13136.14 | J26: =Historical!J8 -> 14136.26 | K26: =Historical!K8 -> 16300.55 | L26: =Historical!L8 -> 16769.27 | M26: =Historical!M8 -> 17942.67 | N26: =M26*(1+N7) -> 19594.956 | O26: =N26*(1+O7) -> 21218.953 | P26: =O26*(1+P7) -> 22801.684 | Q26: =P26*(1+Q7) -> 24332.393 | R26: =Q26*(1+R7) -> 25802.514 | S26: =R26*(1+S7) -> 27205.563
D27: Cost of Goood Sold(COGS) | F27: ₹ in Cr | H27: =-SUM(Historical!H11:H13) -> -6927.47 | I27: =-SUM(Historical!I11:I13) -> -7626.1 | J27: =-SUM(Historical!J11:J13) -> -8760.3 | K27: =-SUM(Historical!K11:K13) -> -9591.3 | L27: =-SUM(Historical!L11:L13) -> -9492.03 | M27: =-SUM(Historical!M11:M13) -> -10604.05 | N27: =-N26*N8 -> -11570.506 | O27: =-O26*O8 -> -12529.45 | P27: =-P26*P8 -> -13464.027 | Q27: =-Q26*Q8 -> -14367.886 | R27: =-R26*R8 -> -15235.969 | S27: =-S26*S8 -> -16064.447
D28: Gross Profit | F28: ₹ in Cr | H28: =SUM(H26:H27) -> 4672.08 | I28: =SUM(I26:I27) -> 5510.04 | J28: =SUM(J26:J27) -> 5375.96 | K28: =SUM(K26:K27) -> 6709.25 | L28: =SUM(L26:L27) -> 7277.24 | M28: =SUM(M26:M27) -> 7338.62 | N28: =SUM(N26:N27) -> 8024.4502 | O28: =SUM(O26:O27) -> 8689.5029 | ... S28: =SUM(S26:S27) -> 11141.116
C29: Expense
D30: Salalries and Benefits | F30: ₹ in Cr | H30: =-Historical!H14 -> -486.69 | I30: =-Historical!I14 -> -527.38 | J30: =-Historical!J14 -> -542.26 | K30: =-Historical!K14 -> -658.38 | L30: =-Historical!L14 -> -708.7 | M30: =-Historical!M14 -> -704.59 | N30: =-N26*N9 -> -791.58812 | O30: =-O26*O9 -> -857.19358 | P30: =-P26*P9 -> -921.13204 | Q30: =-Q26*Q9 -> -982.96893 | R30: =-R26*R9 -> -1042.3582 | S30: =-S26*S9 -> -1099.0379
D31: Other SG&A Expenses | F31: ₹ in Cr | H31: =-SUM(Historical!H17) -> -2342.21 | I31: =-SUM(Historical!I17) -> -2473.37 | J31: =-SUM(Historical!J17) -> -2632.31 | K31: =-SUM(Historical!K17) -> -3219.91 | L31: =-SUM(Historical!L17) -> -3398.46 | M31: =-SUM(Historical!M17) -> -3446.88 | N31: =N26*-N10 -> -3816.832 | O31: =O26*-O10 -> -4133.1645 | P31: =P26*-P10 -> -4441.4591 | Q31: =Q26*-Q10 -> -4739.6205 | R31: =R26*-R10 -> -5025.9802 | S31: =S26*-S10 -> -5299.2751
D32: EBITDA | F32: ₹ in Cr | H32: =SUM(H28:H31) -> 1843.18 | I32: =SUM(I28:I31) -> 2509.29 | J32: =SUM(J28:J31) -> 2201.39 | K32: =SUM(K28:K31) -> 2830.96 | L32: =SUM(L28:L31) -> 3170.08 | M32: =SUM(M28:M31) -> 3187.15 | N32: =SUM(N28:N31) -> 3416.0301 | O32: =SUM(O28:O31) -> 3699.1448 | ... S32: =SUM(S28:S31) -> 4742.8033
D33: Depriciation and Amortization Expense | F33: ₹ in Cr | H33: =-Historical!H16 -> -184.81 | I33: =-Historical!I16 -> -197.85 | J33: =-Historical!J16 -> -200.54 | K33: =-Historical!K16 -> -225.96 | L33: =-Historical!L16 -> -300.7 | M33: =-Historical!M16 -> -313.34 | N33: =N11*-M56 -> -317.16438 | O33: =O11*-N56 -> -335.15262 | P33: =P11*-O56 -> -362.92949 | Q33: =Q11*-P56 -> -390.00057 | R33: =R11*-Q56 -> -416.18186 | S33: =S11*-R56 -> -441.32684
D34: EBIT | F34: ₹ in Cr | H34: =SUM(H32:H33) -> 1658.37 | I34: =SUM(I32:I33) -> 2311.44 | J34: =SUM(J32:J33) -> 2000.85 | K34: =SUM(K32:K33) -> 2605 | L34: =SUM(L32:L33) -> 2869.38 | M34: =SUM(M32:M33) -> 2873.81 | N34: =SUM(N32:N33) -> 3098.8657 | O34: =SUM(O32:O33) -> 3363.9922 | ... S34: =SUM(S32:S33) -> 4301.4764
D35: Interest Expense | F35: ₹ in Cr | H35: =-Historical!H15 -> -76.9 | I35: =-Historical!I15 -> -110.9 | J35: =-Historical!J15 -> -144.29 | K35: =-Historical!K15 -> -169.1 | L35: =-Historical!L15 -> -164 | M35: =-Historical!M15 -> -138.8 | N35: =N12*-AVERAGE(N124,N126) -> -82.88371 | O35: =O12*-N68 -> -82.88371 | P35: =P12*-O68 -> -82.88371 | Q35: =Q12*-P68 -> -82.88371 | R35: =R12*-Q68 -> -82.88371 | S35: =S12*-R68 -> -82.88371
D36: {=Historical!D20:D22} -> Share of profit/(loss) of associates & joint venture | F36: ₹ in Cr | H36: =Historical!H20 -> 0.44 | I36: =Historical!I20 -> 0.81 | J36: =Historical!J20 -> -0.2 | K36: =Historical!K20 -> 5.41 | L36: =Historical!L20 -> -3.19 | M36: =Historical!M20 -> -10.74 | N36: =AVERAGE(K36:M36) -> -2.84 | O36: =AVERAGE(L36:N36) -> -5.59 | P36: =AVERAGE(M36:O36) -> -6.39 | Q36: =AVERAGE(N36:P36) -> -4.94 | R36: =AVERAGE(O36:Q36) -> -5.64 | S36: =AVERAGE(P36:R36) -> -5.6566667
D37: Profit before exceptional items and tax | F37: ₹ in Cr | H37: =SUM(H34:H36) -> 1581.91 | I37: =SUM(I34:I36) -> 2201.35 | J37: =SUM(J34:J36) -> 1856.36 | K37: =SUM(K34:K36) -> 2441.31 | L37: =SUM(L34:L36) -> 2702.19 | M37: =SUM(M34:M36) -> 2724.27 | N37: =SUM(N34:N36) -> 3013.142 | O37: =SUM(O34:O36) -> 3275.5185 | ... S37: =SUM(S34:S36) -> 4212.936
D38: Exceptional items | F38: ₹ in Cr | H38: =-Historical!H22 -> -17.01 | I38: =-Historical!I22 -> -0.61 | J38: =-Historical!J22 -> -0.98 | K38: =-Historical!K22 -> 375.6 | L38: =-Historical!L22 -> -2.9 | M38: =-Historical!M22 -> -24.79 | N38: 0 | O38: 0 | P38: 0 | Q38: 0 | R38: 0 | S38: 0
D39: Other Income | F39: ₹ in Cr | H39: =Historical!H9 -> 279.4 | I39: =Historical!I9 -> 312.87 | J39: =Historical!J9 -> 222.83 | K39: =Historical!K9 -> 215.86 | L39: =Historical!L9 -> 214.18 | M39: =Historical!M9 -> 227.09 | N39: =N13*N26 -> 334.22053 | O39: =O13*O26 -> 361.92015 | P39: =P13*P26 -> 388.91594 | Q39: =Q13*Q26 -> 415.02441 | R39: =R13*R26 -> 440.09947 | S39: =S13*S26 -> 464.03051
D40: Earnings Before Tax | F40: ₹ in Cr | H40: =SUM(H37:H39) -> 1844.3 | I40: =SUM(I37:I39) -> 2513.61 | J40: =SUM(J37:J39) -> 2078.21 | K40: =SUM(K37:K39) -> 3032.77 | L40: =SUM(L37:L39) -> 2913.47 | M40: =SUM(M37:M39) -> 2926.57 | N40: =SUM(N37:N39) -> 3347.3626 | O40: =SUM(O37:O39) -> 3637.4386 | ... S40: =SUM(S37:S39) -> 4676.9666
D41: Taxes | F41: ₹ in Cr | H41: =-SUM(Historical!H24:H25) -> -450.7 | I41: =-SUM(Historical!I24:I25) -> -663.02 | J41: =-SUM(Historical!J24:J25) -> -562.35 | K41: =-SUM(Historical!K24:K25) -> -716.45 | L41: =-SUM(Historical!L24:L25) -> -779.25 | M41: =-SUM(Historical!M24:M25) -> -748.71 | N41: =-(N14)*N40 -> -858.19273 | O41: =-(O14)*O40 -> -932.56209 | P41: =-(P14)*P40 -> -1002.897 | Q41: =-(Q14)*Q40 -> -1071.4371 | R41: =-(R14)*R40 -> -1136.6811 | S41: =-(S14)*S40 -> -1199.075
D42: Net Earnings | F42: ₹ in Cr | H42: =SUM(H40:H41) -> 1393.6 | I42: =SUM(I40:I41) -> 1850.59 | J42: =SUM(J40:J41) -> 1515.86 | K42: =SUM(K40:K41) -> 2316.32 | L42: =SUM(L40:L41) -> 2134.22 | M42: =SUM(M40:M41) -> 2177.86 | N42: =SUM(N40:N41) -> 2489.1698 | O42: =SUM(O40:O41) -> 2704.8766 | ... S42: =SUM(S40:S41) -> 3477.8916
A44: Balancesheet
B46: Assets
C47: Current Assets
D48: Cash | F48: ₹ in Cr | H48: =Historical!H52 -> 81.23 | I48: =Historical!I52 -> 142.74 | J48: =Historical!J52 -> 117.99 | K48: =Historical!K52 -> 102.38 | L48: =Historical!L52 -> 322.8 | M48: =Historical!M52 -> 132.72 | N48: =N106 -> 497.70334 | O48: =O106 -> 989.87065 | P48: =P106 -> 1541.3375 | Q48: =Q106 -> 2152.1904 | R48: =R106 -> 2821.0726 | S48: =S106 -> 3546.6858
D49: Bank Deposits | F49: ₹ in Cr | H49: =Historical!H53 -> 41.62 | I49: =Historical!I53 -> 68.6 | J49: =Historical!J53 -> 66.91 | K49: =Historical!K53 -> 95.6 | L49: =Historical!L53 -> 123.55 | M49: =Historical!M53 -> 179.7 | N49: =M49 -> 179.7 | O49: =N49 -> 179.7 | P49: =O49 -> 179.7 | Q49: =P49 -> 179.7 | R49: =Q49 -> 179.7 | S49: =R49 -> 179.7
D50: Accounts Receivables | F50: ₹ in Cr | H50: =Historical!H51 -> 320.36 | I50: =Historical!I51 -> 257.27 | J50: =Historical!J51 -> 331.93 | K50: =Historical!K51 -> 328.94 | L50: =Historical!L51 -> 393.33 | M50: =Historical!M51 -> 448.61 | N50: =N16*N26/365 -> 454.99967 | O50: =O16*O26/365 -> 492.70927 | P50: =P16*P26/365 -> 529.46067 | Q50: =Q16*Q26/365 -> 565.00411 | R50: =R16*R26/365 -> 599.14068 | S50: =S16*S26/365 -> 631.71982
D51: Loan Recievables | F51: ₹ in Cr | H51: =Historical!H54 -> 1110.11 | I51: =Historical!I54 -> 946.56 | J51: =Historical!J54 -> 698 | K51: =Historical!K54 -> 560 | L51: =Historical!L54 -> 460 | M51: =Historical!M54 -> 50 | N51: =M51 -> 50 | O51: =N51 -> 50 | P51: =O51 -> 50 | Q51: =P51 -> 50 | R51: =Q51 -> 50 | S51: =R51 -> 50
D52: Inventory | F52: ₹ in Cr | H52: =Historical!H48 -> 740.96 | I52: =Historical!I48 -> 1091.49 | J52: =Historical!J48 -> 1367.49 | K52: =Historical!K48 -> 1193.18 | L52: =Historical!L48 -> 1181.22 | M52: =Historical!M48 -> 1236.51 | N52: =N17*-N27/365 -> 1488.0425 | O52: =O17*-O27/365 -> 1611.3689 | P52: =P17*-P27/365 -> 1731.5616 | Q52: =Q17*-Q27/365 -> 1847.8038 | R52: =R17*-R27/365 -> 1959.4449 | S52: =S17*-S27/365 -> 2065.9925
D53: Investments | F53: ₹ in Cr | H53: =Historical!H50 -> 1008.77 | I53: =Historical!I50 -> 1393.25 | J53: =Historical!J50 -> 833.73 | K53: =Historical!K50 -> 1800.99 | L53: =Historical!L50 -> 1696.51 | M53: =Historical!M50 -> 1111.64 | N53: =M53 -> 1111.64 | O53: =N53 -> 1111.64 | P53: =O53 -> 1111.64 | Q53: =P53 -> 1111.64 | R53: =Q53 -> 1111.64 | S53: =R53 -> 1111.64
D54: Other Current Assets | F54: ₹ in Cr | H54: =SUM(Historical!H55,Historical!H56,Historical!H57) -> 371.92 | I54: =SUM(Historical!I55,Historical!I56,Historical!I57) -> 519.77 | J54: =SUM(Historical!J55,Historical!J56,Historical!J57) -> 566.25 | K54: =SUM(Historical!K55,Historical!K56,Historical!K57) -> 665.06 | L54: =SUM(Historical!L55,Historical!L56,Historical!L57) -> 671.25 | M54: =SUM(Historical!M55,Historical!M56,Historical!M57) -> 754.44 | N54: =M54 -> 754.44 | O54: =N54 -> 754.44 | P54: =O54 -> 754.44 | Q54: =P54 -> 754.44 | R54: =Q54 -> 754.44 | S54: =R54 -> 754.44
C55: Non-Current Assets
D56: Property & Equiipments | F56: ₹ in Cr | H56: =Historical!H33+Historical!H34+Historical!H35+Historical!H37 -> 1778.76 | I56: =Historical!I33+Historical!I34+Historical!I35+Historical!I37 -> 1773.57 | J56: =Historical!J33+Historical!J34+Historical!J35+Historical!J37 -> 2149.28 | K56: =Historical!K33+Historical!K34+Historical!K35+Historical!K37 -> 2632.14 | L56: =Historical!L33+Historical!L34+Historical!L35+Historical!L37 -> 2828.86 | M56: =Historical!M33+Historical!M34+Historical!M35+Historical!M37 -> 2860.22 | N56: =N121 -> 3022.4397 | O56: =O121 -> 3272.9343 | P56: =P121 -> 3517.064 | Q56: =Q121 -> 3753.1694 | R56: =R121 -> 3979.9294 | S56: =S121 -> 4196.3438
D57: Goodwill | F57: ₹ in Cr | H57: =Historical!H36 -> 138.97 | I57: =Historical!I36 -> 135.9 | J57: =Historical!J36 -> 139.61 | K57: =Historical!K36 -> 128.16 | L57: =Historical!L36 -> 129.82 | M57: =Historical!M36 -> 132.78 | N57: =M57 -> 132.78 | O57: =N57 -> 132.78 | P57: =O57 -> 132.78 | Q57: =P57 -> 132.78 | R57: =Q57 -> 132.78 | S57: =R57 -> 132.78
D58: Financial Assets | F58: ₹ in Cr | H58: =SUM(Historical!H40:H42) -> 2117.26 | I58: =SUM(Historical!I40:I42) -> 1489.86 | J58: =SUM(Historical!J40:J42) -> 1058.35 | K58: =SUM(Historical!K40:K42) -> 1201.66 | L58: =SUM(Historical!L40:L42) -> 601.35 | M58: =SUM(Historical!M40:M42) -> 1323.36 | N58: =M58 -> 1323.36 | O58: =N58 -> 1323.36 | P58: =O58 -> 1323.36 | Q58: =P58 -> 1323.36 | R58: =Q58 -> 1323.36 | S58: =R58 -> 1323.36
D59: Investment in associates and joint ventures | F59: ₹ in Cr | H59: =Historical!H38 -> 1.48 | I59: =Historical!I38 -> 2.29 | J59: =Historical!J38 -> 2.09 | K59: =Historical!K38 -> 495.16 | L59: =Historical!L38 -> 494.36 | M59: =Historical!M38 -> 483.62 | N59: =M59 -> 483.62 | O59: =N59 -> 483.62 | P59: =O59 -> 483.62 | Q59: =P59 -> 483.62 | R59: =Q59 -> 483.62 | S59: =R59 -> 483.62
D60: Other Non Current Assets | F60: ₹ in Cr | H60: =SUM(Historical!H43:H45) -> 130.79 | I60: =SUM(Historical!I43:I45) -> 187.48 | J60: =SUM(Historical!J43:J45) -> 195.78 | K60: =SUM(Historical!K43:K45) -> 149.45 | L60: =SUM(Historical!L43:L45) -> 170.51 | M60: =SUM(Historical!M43:M45) -> 124.95 | N60: =M60 -> 124.95 | O60: =N60 -> 124.95 | P60: =O60 -> 124.95 | Q60: =P60 -> 124.95 | R60: =Q60 -> 124.95 | S60: =R60 -> 124.95
D61: Total Assets | F61: ₹ in Cr | H61: =SUM(H48:H60) -> 7842.23 | I61: =SUM(I48:I60) -> 8008.78 | J61: =SUM(J48:J60) -> 7527.41 | K61: =SUM(K48:K60) -> 9352.72 | L61: =SUM(L48:L60) -> 9073.56 | M61: =SUM(M48:M60) -> 8838.55 | N61: =SUM(N48:N60) -> 9623.6752 | O61: =SUM(O48:O60) -> 10527.373 | ... S61: =SUM(S48:S60) -> 14601.232
B63: Liabilities
C64: Current Liabilities
D65: Accounts Payables | F65: ₹ in Cr | H65: =SUM(Historical!H80:H82) -> 1047 | I65: =SUM(Historical!I80:I83) -> 1670.76 | J65: =SUM(Historical!J80:J83) -> 1716.77 | K65: =SUM(Historical!K80:K83) -> 1945.02 | L65: =SUM(Historical!L80:L83) -> 2124.88 | M65: =SUM(Historical!M80:M83) -> 2181.57 | N65: =N18*N27/-365 -> 2311.349 | O65: =O18*O27/-365 -> 2502.9096 | P65: =P18*P27/-365 -> 2689.6028 | Q65: =Q18*Q27/-365 -> 2870.1596 | R65: =R18*R27/-365 -> 3043.5696 | S65: =S18*S27/-365 -> 3209.0681
D66: Other Current Liabilities | F66: ₹ in Cr | H66: =SUM(Historical!H83:H86) -> 783.47 | I66: =SUM(Historical!I84:I86) -> 604.09 | J66: =SUM(Historical!J84:J86) -> 669.92 | K66: =SUM(Historical!K84:K86) -> 758.17 | L66: =SUM(Historical!L84:L86) -> 819.42 | M66: =SUM(Historical!M84:M86) -> 922.57 | N66: =M66 -> 922.57 | O66: =N66 -> 922.57 | P66: =O66 -> 922.57 | Q66: =P66 -> 922.57 | R66: =Q66 -> 922.57 | S66: =R66 -> 922.57
C67: Non-Current Liabilities
D68: Debt | F68: ₹ in Cr | H68: =Historical!H70+Historical!H71+Historical!H78+Historical!H79 -> 1514.05 | I68: =Historical!I70+Historical!I71+Historical!I78+Historical!I79 -> 2087.17 | J68: =Historical!J70+Historical!J71+Historical!J78+Historical!J79 -> 2481.2 | K68: =Historical!K70+Historical!K71+Historical!K78+Historical!K79 -> 2997.37 | L68: =Historical!L70+Historical!L71+Historical!L78+Historical!L79 -> 2064.96 | M68: =Historical!M70+Historical!M71+Historical!M78+Historical!M79 -> 1246.51 | N68: =M68 -> 1246.51 | O68: =N68 -> 1246.51 | P68: =O68 -> 1246.51 | Q68: =P68 -> 1246.51 | R68: =Q68 -> 1246.51 | S68: =R68 -> 1246.51
D69: Other Non Current Liabilities | F69: ₹ in Cr | H69: =Historical!H74+Historical!H72+Historical!H73 -> 59.23 | I69: =Historical!I74+Historical!I72+Historical!I73 -> 62.76 | J69: =Historical!J74+Historical!J72+Historical!J73 -> 73.92 | K69: =Historical!K74+Historical!K72+Historical!K73 -> 87.66 | L69: =Historical!L74+Historical!L72+Historical!L73 -> 98.28 | M69: =Historical!M74+Historical!M72+Historical!M73 -> 106.58 | N69: =M69 -> 106.58 | O69: =N69 -> 106.58 | P69: =O69 -> 106.58 | Q69: =P69 -> 106.58 | R69: =Q69 -> 106.58 | S69: =R69 -> 106.58
D70: Total Liabilities | F70: ₹ in Cr | H70: =SUM(H65:H69) -> 3403.75 | I70: =SUM(I65:I69) -> 4424.78 | J70: =SUM(J65:J69) -> 4941.81 | K70: =SUM(K65:K69) -> 5788.22 | L70: =SUM(L65:L69) -> 5107.54 | M70: =SUM(M65:M69) -> 4457.23 | N70: =SUM(N65:N69) -> 4587.009 | O70: =SUM(O65:O69) -> 4778.5696 | ... S70: =SUM(S65:S69) -> 5484.7281
C71: Shareholder's Equity
D72: Equity Capital | F72: ₹ in Cr | H72: =Historical!H62 -> 24.05 | I72: =Historical!I62 -> 24.09 | J72: =Historical!J62 -> 24.09 | K72: =Historical!K62 -> 24.09 | L72: =Historical!L62 -> 24.09 | M72: =Historical!M62 -> 24.09 | N72: =M72 -> 24.09 | O72: =N72 -> 24.09 | P72: =O72 -> 24.09 | Q72: =P72 -> 24.09 | R72: =Q72 -> 24.09 | S72: =R72 -> 24.09
D73: Retained Earnings | F73: ₹ in Cr | H73: =Historical!H63 -> 4378.78 | I73: =Historical!I63 -> 3523.57 | J73: =Historical!J63 -> 2534.01 | K73: =Historical!K63 -> 3510.18 | L73: =Historical!L63 -> 3917.43 | M73: =Historical!M63 -> 4331.63 | N73: =M73+N42+N101 -> 4986.9762 | O73: =N73+O42+O101 -> 5699.1135 | P73: =O73+P42+P101 -> 6464.961 | Q73: =P73+Q42+Q101 -> 7283.1481 | R73: =Q73+R42+R101 -> 8151.1579 | S73: =R73+S42+S101 -> 9066.8138
D74: Total Shareholder's Equity | F74: ₹ in Cr | H74: =SUM(H72:H73) -> 4402.83 | I74: =SUM(I72:I73) -> 3547.66 | J74: =SUM(J72:J73) -> 2558.1 | K74: =SUM(K72:K73) -> 3534.27 | L74: =SUM(L72:L73) -> 3941.52 | M74: =SUM(M72:M73) -> 4355.72 | N74: =SUM(N72:N73) -> 5011.0662 | O74: =SUM(O72:O73) -> 5723.2035 | ... S74: =SUM(S72:S73) -> 9090.9038
D75: Non Controlling Interest | F75: ₹ in Cr | H75: =Historical!H65 -> 35.65 | I75: =Historical!I65 -> 36.34 | J75: =Historical!J65 -> 27.5 | K75: =Historical!K65 -> 30.23 | L75: =Historical!L65 -> 24.5 | M75: =Historical!M65 -> 25.6 | N75: =M75 -> 25.6 | O75: =N75 -> 25.6 | P75: =O75 -> 25.6 | Q75: =P75 -> 25.6 | R75: =Q75 -> 25.6 | S75: =R75 -> 25.6
D76: Total Liabilities & Shahreholder Equity | F76: ₹ in Cr | H76: =SUM(H74:H75,H70) -> 7842.23 | I76: =SUM(I74:I75,I70) -> 8008.78 | J76: =SUM(J74:J75,J70) -> 7527.41 | K76: =SUM(K74:K75,K70) -> 9352.72 | L76: =SUM(L74:L75,L70) -> 9073.56 | M76: =SUM(M74:M75,M70) -> 8838.55 | N76: =SUM(N74:N75,N70) -> 9623.6752 | O76: =SUM(O74:O75,O70) -> 10527.373 | ... S76: =SUM(S74:S75,S70) -> 14601.232
D77: Check | H77: =H76-H61 -> 0 | I77: =I76-I61 -> 0 | J77: =J76-J61 -> 0 | K77: =K76-K61 -> 0 | L77: =L76-L61 -> 0 | M77: =M76-M61 -> 0 | N77: =N76-N61 -> 0 | O77: =O76-O61 -> 0 | ... S77: =S76-S61 -> 0
A78: Cashflow Statement
B80: Cashflow from Operating Acitvities
D81: Net Income | F81: ₹ in Cr | H81: =Historical!H94 -> 1843.86 | I81: =Historical!I94 -> 2512.8 | J81: =Historical!J94 -> 2078.53 | K81: =Historical!K94 -> 3027.36 | L81: =Historical!L94 -> 2916.66 | M81: =Historical!M94 -> 2937.31 | N81: =N40 -> 3347.3626 | O81: =O40 -> 3637.4386 | P81: =P40 -> 3911.7785 | Q81: =Q40 -> 4179.1176 | R81: =R40 -> 4433.6007 | S81: =S40 -> 4676.9666
D82: (+/-) Depriciation&Amortisation | F82: ₹ in Cr | H82: =Historical!H95 -> 184.81 | I82: =Historical!I95 -> 197.85 | J82: =Historical!J95 -> 200.54 | K82: =Historical!K95 -> 225.91 | L82: =Historical!L95 -> 300.46 | M82: =Historical!M95 -> 313.34 | N82: =N11*M56 -> 317.16438 | O82: =O11*N56 -> 335.15262 | P82: =P11*O56 -> 362.92949 | Q82: =Q11*P56 -> 390.00057 | R82: =R11*Q56 -> 416.18186 | S82: =S11*R56 -> 441.32684
D83: (+/-) Non Cash Expenses | F83: ₹ in Cr | H83: =Historical!H96+Historical!H101+Historical!H100 -> -78.29 | I83: =Historical!I96+Historical!I101+Historical!I100 -> -104.82 | J83: =Historical!J96+Historical!J101+Historical!J100 -> -35.53 | K83: =Historical!K96+Historical!K101+Historical!K100 -> 11.54 | L83: =Historical!L96+Historical!L101+Historical!L100 -> -14.75 | M83: =Historical!M96+Historical!M101+Historical!M100 -> 6 | N83: =-N35 -> 82.88371 | O83: =-O35 -> 82.88371 | P83: =-P35 -> 82.88371 | Q83: =-Q35 -> 82.88371 | R83: =-R35 -> 82.88371 | S83: =-S35 -> 82.88371
D84: (+/-) Non Operating Losses | F84: ₹ in Cr | H84: =Historical!H98+Historical!H99+Historical!H97 -> -89.99 | I84: =Historical!I98+Historical!I99+Historical!I97 -> -65.8 | J84: =Historical!J98+Historical!J99+Historical!J97 -> -29.86 | K84: =Historical!K98+Historical!K99+Historical!K97 -> -418.51 | L84: =Historical!L98+Historical!L99+Historical!L97 -> -25.62 | M84: =Historical!M98+Historical!M99+Historical!M97 -> -82.59 | N84: =-N39 -> -334.22053 | O84: =-O39 -> -361.92015 | P84: =-P39 -> -388.91594 | Q84: =-Q39 -> -415.02441 | R84: =-R39 -> -440.09947 | S84: =-S39 -> -464.03051
D85: (+/-) Change In Working Capital | F85: ₹ in Cr | H85: =SUM(Historical!H102:H106) -> 127.39 | I85: =SUM(Historical!I102:I106) -> -56.15 | J85: =SUM(Historical!J102:J106) -> -327.25 | K85: =SUM(Historical!K102:K106) -> 405.66 | L85: =SUM(Historical!L102:L106) -> 161.1 | M85: =SUM(Historical!M102:M106) -> -4.2 | N85: =N115 -> -128.14318 | O85: =O115 -> 30.524637 | P85: =P115 -> 29.749019 | Q85: =Q115 -> 28.771211 | R85: =R115 -> 27.632397 | S85: =S115 -> 26.371708
C86: Cashflow From Operating Activities | F86: ₹ in Cr | H86: =SUM(H81:H85) -> 1987.78 | I86: =SUM(I81:I85) -> 2483.88 | J86: =SUM(J81:J85) -> 1886.43 | K86: =SUM(K81:K85) -> 3251.96 | L86: =SUM(L81:L85) -> 3337.85 | M86: =SUM(M81:M85) -> 3169.86 | N86: =SUM(N81:N85) -> 3285.0469 | O86: =SUM(O81:O85) -> 3724.0795 | ... S86: =SUM(S81:S85) -> 4763.5183
D87: (-) Income Tax | F87: ₹ in Cr | H87: =Historical!H108 -> -503.25 | I87: =Historical!I108 -> -632.81 | J87: =Historical!J108 -> -586.91 | K87: =Historical!K108 -> -725.75 | L87: =Historical!L108 -> -764.87 | M87: =Historical!M108 -> -689.21 | N87: =N41 -> -858.19273 | O87: =O41 -> -932.56209 | P87: =P41 -> -1002.897 | Q87: =Q41 -> -1071.4371 | R87: =R41 -> -1136.6811 | S87: =S41 -> -1199.075
C88: Net Cashflow From Operations | F88: ₹ in Cr | H88: =SUM(H86:H87) -> 1484.53 | I88: =SUM(I86:I87) -> 1851.07 | J88: =SUM(J86:J87) -> 1299.52 | K88: =SUM(K86:K87) -> 2526.21 | L88: =SUM(L86:L87) -> 2572.98 | M88: =SUM(M86:M87) -> 2480.65 | N88: =SUM(N86:N87) -> 2426.8542 | O88: =SUM(O86:O87) -> 2791.5174 | ... S88: =SUM(S86:S87) -> 3564.4433
C90: Cashflow from Investing Activities
D91: (-) Investments in Properties and equipment | F91: ₹ in Cr | H91: =SUM(Historical!H111,Historical!H113) -> -244.17 | I91: =SUM(Historical!I111,Historical!I113) -> -242.07 | J91: =SUM(Historical!J111,Historical!J113) -> -550.18 | K91: =SUM(Historical!K111,Historical!K113) -> -712.91 | L91: =SUM(Historical!L111,Historical!L113) -> -743.77 | M91: =SUM(Historical!M111,Historical!M113) -> -1319.9 | N91: =-N119 -> -479.38408 | O91: =-O119 -> -585.64723 | P91: =-P119 -> -607.05915 | Q91: =-Q119 -> -626.10603 | R91: =-R119 -> -642.94185 | S91: =-S119 -> -657.74124
D92: (+) Sale of Property plant and Equipment | F92: ₹ in Cr | H92: =Historical!H112+Historical!H114 -> 0.73 | I92: =Historical!I112+Historical!I114 -> 2.17 | J92: =Historical!J112+Historical!J114 -> 3.16 | K92: =Historical!K112+Historical!K114 -> 78.43 | L92: =Historical!L112+Historical!L114 -> 358.74 | M92: =Historical!M112+Historical!M114 -> 576.74 | N92: 0 | O92: 0 | P92: 0 | Q92: 0 | R92: 0 | S92: 0
D93: (+) Investment Made in Instruments | F93: ₹ in Cr | H93: =Historical!H116+Historical!H119+Historical!H120+Historical!H118 -> -89.17 | I93: =Historical!I116+Historical!I119+Historical!I120+Historical!I118 -> 288.91 | J93: =Historical!J116+Historical!J119+Historical!J120+Historical!J118 -> 393.28 | K93: =Historical!K116+Historical!K119+Historical!K120+Historical!K118 -> 439.57 | L93: =Historical!L116+Historical!L119+Historical!L120+Historical!L118 -> 250 | M93: =Historical!M116+Historical!M119+Historical!M120+Historical!M118 -> 385 | N93: 0 | O93: 0 | P93: 0 | Q93: 0 | R93: 0 | S93: 0
D94: (-) Sale of investments | F94: ₹ in Cr | H94: =Historical!H115+Historical!H117 -> -1326.63 | I94: =Historical!I115+Historical!I117 -> 178.82 | J94: =Historical!J115+Historical!J117 -> 856.19 | K94: =Historical!K115+Historical!K117 -> -1468.14 | L94: =Historical!L115+Historical!L117 -> 476.87 | M94: =Historical!M115+Historical!M117 -> 347.31 | N94: 0 | O94: 0 | P94: 0 | Q94: 0 | R94: 0 | S94: 0
D95: (+) Interest and Dividend received | F95: ₹ in Cr | H95: =Historical!H122+Historical!H121 -> 127.62 | I95: =Historical!I122+Historical!I121 -> 233.43 | J95: =Historical!J122+Historical!J121 -> 208.44 | K95: =Historical!K122+Historical!K121 -> 145.99 | L95: =Historical!L122+Historical!L121 -> 142.31 | M95: =Historical!M122+Historical!M121 -> 95.21 | N95: =N39 -> 334.22053 | O95: =O39 -> 361.92015 | P95: =P39 -> 388.91594 | Q95: =Q39 -> 415.02441 | R95: =R39 -> 440.09947 | S95: =S39 -> 464.03051
D96: Cash From Investing Activity | F96: ₹ in Cr | H96: =SUM(H91:H95) -> -1531.62 | I96: =SUM(I91:I95) -> 461.26 | J96: =SUM(J91:J95) -> 910.89 | K96: =SUM(K91:K95) -> -1517.06 | L96: =SUM(L91:L95) -> 484.15 | M96: =SUM(M91:M95) -> 84.36 | N96: =SUM(N91:N95) -> -145.16355 | O96: =SUM(O91:O95) -> -223.72708 | ... S96: =SUM(S91:S95) -> -193.71073
C98: Cashflow from Financing Activities
D99: Issuance of debt repayment | F99: ₹ in Cr | H99: =SUM(Historical!H126:H129,Historical!H137) -> -871.18 | I99: =SUM(Historical!I126:I129,Historical!I137) -> -2.55 | J99: =SUM(Historical!J126:J129,Historical!J137) -> -985.57 | K99: =SUM(Historical!K126:K129,Historical!K137) -> -793.94 | L99: =SUM(Historical!L126:L129,Historical!L137) -> -115.55 | M99: =SUM(Historical!M126:M129,Historical!M137) -> -850.63 | N99: 0 | O99: 0 | P99: 0 | Q99: 0 | R99: 0 | S99: 0
D100: Proceeds from share allotment | F100: ₹ in Cr | H100: =Historical!H125+Historical!H132+Historical!H134+Historical!H133 -> 1385.64 | I100: =Historical!I125+Historical!I132+Historical!I134+Historical!I133 -> 670.95 | J100: =Historical!J125+Historical!J132+Historical!J134+Historical!J133 -> 1343.87 | K100: =Historical!K125+Historical!K132+Historical!K134+Historical!K133 -> 1312.09 | L100: =Historical!L125+Historical!L132+Historical!L134+Historical!L133 -> -826.64 | M100: =Historical!M125+Historical!M132+Historical!M134+Historical!M133 -> 26.26 | N100: 0 | O100: 0 | P100: 0 | Q100: 0 | R100: 0 | S100: 0
D101: Dividend Paid | F101: ₹ in Cr | H101: =SUM(Historical!H136) -> -432.53 | I101: =SUM(Historical!I136) -> -2823.75 | J101: =SUM(Historical!J136) -> -2484.88 | K101: =SUM(Historical!K136) -> -1359.24 | L101: =SUM(Historical!L136) -> -1732.47 | M101: =SUM(Historical!M136) -> -1767.54 | N101: =-N42*N15 -> -1833.8236 | O101: =-O42*O15 -> -1992.7393 | P101: =-P42*P15 -> -2143.034 | Q101: =-Q42*Q15 -> -2289.4934 | R101: =-R42*R15 -> -2428.9098 | S101: =-S42*S15 -> -2562.2356
D102: Interest Paid | F102: ₹ in Cr | H102: =SUM(Historical!H131,Historical!H130,Historical!H135) -> -23.99 | I102: =SUM(Historical!I131,Historical!I130,Historical!I135) -> -88.34 | J102: =SUM(Historical!J131,Historical!J130,Historical!J135) -> -119.26 | K102: =SUM(Historical!K131,Historical!K130,Historical!K135) -> -187.28 | L102: =SUM(Historical!L131,Historical!L130,Historical!L135) -> -164.47 | M102: =SUM(Historical!M131,Historical!M130,Historical!M135) -> -169.95 | N102: =N127 -> -82.88371 | O102: =O127 -> -82.88371 | P102: =P127 -> -82.88371 | Q102: =Q127 -> -82.88371 | R102: =R127 -> -82.88371 | S102: =S127 -> -82.88371
D103: Cash From Financing Activities | F103: ₹ in Cr | H103: =SUM(H99:H102) -> 57.94 | I103: =SUM(I99:I102) -> -2243.69 | J103: =SUM(J99:J102) -> -2245.84 | K103: =SUM(K99:K102) -> -1028.37 | L103: =SUM(L99:L102) -> -2839.13 | M103: =SUM(M99:M102) -> -2761.86 | N103: =SUM(N99:N102) -> -1916.7073 | O103: =SUM(O99:O102) -> -2075.623 | ... S103: =SUM(S99:S102) -> -2645.1194
B104: Net Cashflow | F104: ₹ in Cr | H104: =H103+H96+H88 -> 10.85 | I104: =I103+I96+I88 -> 68.64 | J104: =J103+J96+J88 -> -35.43 | K104: =K103+K96+K88 -> -19.22 | L104: =L103+L96+L88 -> 218 | M104: =M103+M96+M88 -> -196.85 | N104: =N103+N96+N88 -> 364.98334 | O104: =O103+O96+O88 -> 492.16731 | ... S104: =S103+S96+S88 -> 725.61323
D105: Opening Cash Balance | F105: ₹ in Cr | H105: =Historical!H141+Historical!H142 -> 64.41 | I105: =Historical!I141+Historical!I142 -> 72.82 | J105: =Historical!J141+Historical!J142 -> 144.75 | K105: =Historical!K141+Historical!K142 -> 119.38 | L105: =Historical!L141+Historical!L142 -> 101.45 | M105: =Historical!M141+Historical!M142 -> 322.09 | N105: =M48 -> 132.72 | O105: =N48 -> 497.70334 | P105: =O48 -> 989.87065 | Q105: =P48 -> 1541.3375 | R105: =Q48 -> 2152.1904 | S105: =R48 -> 2821.0726
D106: Closing Cash Balance | F106: ₹ in Cr | H106: =SUM(H104:H105) -> 75.26 | I106: =SUM(I104:I105) -> 141.46 | J106: =SUM(J104:J105) -> 109.32 | K106: =SUM(K104:K105) -> 100.16 | L106: =SUM(L104:L105) -> 319.45 | M106: =SUM(M104:M105) -> 125.24 | N106: =SUM(N104:N105) -> 497.70334 | O106: =SUM(O104:O105) -> 989.87065 | ... S106: =SUM(S104:S105) -> 3546.6858
A108: Supporting Schedules
C110: Working Capital
D111: Accounts Recievable | F111: ₹ in Cr | H111: =Historical!H103 -> 78.85 | I111: =Historical!I103 -> 61.4 | J111: =Historical!J103 -> -72.21 | K111: =Historical!K103 -> 1.29 | L111: =Historical!L103 -> -63.65 | M111: =Historical!M103 -> -53.44 | N111: =M50-N50 -> -6.3896734 | O111: =N50-O50 -> -37.709592 | P111: =O50-P50 -> -36.751408 | Q111: =P50-Q50 -> -35.543441 | R111: =Q50-R50 -> -34.13657 | S111: =R50-S50 -> -32.579138
D112: Inventory | F112: ₹ in Cr | H112: =Historical!H102 -> 42.99 | I112: =Historical!I102 -> -351.44 | J112: =Historical!J102 -> -274.76 | K112: =Historical!K102 -> 177.15 | L112: =Historical!L102 -> 12.6 | M112: =Historical!M102 -> -54.33 | N112: =M52-N52 -> -251.53246 | O112: =N52-O52 -> -123.3264 | P112: =O52-P52 -> -120.19274 | Q112: =P52-Q52 -> -116.24217 | R112: =Q52-R52 -> -111.6411 | S112: =R52-S52 -> -106.54764
...

Sheet Scenario Analysis
A1: Britannia Industries Limited
A2: Scenarios
C4: Scenarios | E4: Growth | H4: 2026 | I4: =H4+1 -> 2027 | J4: =I4+1 -> 2028 | K4: =J4+1 -> 2029 | L4: =K4+1 -> 2030 | M4: =L4+1 -> 2031
D5: Base Case | E5: =AVERAGE(Model!I7:M7) -> 0.092086981 | H5: {=E5:E7} -> 0.092086981 | I5: =H5*(1-$E$8) -> 0.082878283 | J5: =I5*(1-$E$8) -> 0.074590454 | K5: =J5*(1-$E$8) -> 0.067131409 | L5: =K5*(1-$E$8) -> 0.060418268 | M5: =L5*(1-$E$8) -> 0.054376441
D6: Bull Case | E6: =MAX(Model!H7:M7) -> 0.15310202 | H6: 0.15310202 | I6: =H6*(1-$E$8) -> 0.13779182 | J6: =I6*(1-$E$8) -> 0.12401264 | K6: =J6*(1-$E$8) -> 0.11161137 | L6: =K6*(1-$E$8) -> 0.10045024 | M6: =L6*(1-$E$8) -> 0.090405213
D7: Bear Case | E7: 0.05 | H7: 0.05 | I7: =H7*(1-$E$8) -> 0.045 | J7: =I7*(1-$E$8) -> 0.0405 | K7: =J7*(1-$E$8) -> 0.03645 | L7: =K7*(1-$E$8) -> 0.032805 | M7: =L7*(1-$E$8) -> 0.0295245
D8: Annual Growth Tapering | E8: 0.1

Sheet Comp Data
B2: S.No. | C2: Name | D2: CMP Rs. | E2: P/E | F2: Mar Cap Rs.Cr. | G2: Qtr Profit Var % | H2: Sales Qtr Rs.Cr. | I2: ROCE % | J2: EV / EBITDA | K2: No. Eq. Shares Cr. | L2: No. Eq. Shares PY Cr. | M2: Debt Rs.Cr. | N2: Debt / Eq | O2: EV Rs.Cr. | P2: CMP / FCF | Q2: EBIDT Ann Rs.Cr. | R2: PAT 12M Rs.Cr. | S2: Levered Beta | T2: Sales | U2: Earnings
B3: 1 | C3: Nestle India | D3: 1484.4 | E3: 82.98 | F3: 286238.95 | G3: 28.84 | H3: 6747.79 | I3: 84.21 | J3: 53.37 | K3: 192.83 | L3: 192.83 | M3: 444.16 | N3: 0.08 | O3: 285342.24 | P3: 115.27 | Q3: 5346.41 | R3: 3451.73 | S3: 0.51 | T3: 23154.6 | U3: 3451.73
B4: =B3+1 -> 2 | C4: Britannia Inds. | D4: 5517.8 | E4: 52.44 | F4: 132906.25 | G4: 21.14 | H4: 4718.92 | I4: 56.02 | J4: 35.83 | K4: 24.09 | L4: 24.09 | M4: 1380.28 | N4: 0.27 | O4: 133934.09 | P4: 60.39 | Q4: 3738.37 | R4: 2533.49 | S4: 0.435 | T4: 19151.59 | U4: 2537.01
B5: =B4+1 -> 3 | C5: Bikaji Foods | D5: 673.3 | E5: 67.61 | F5: 16882.09 | G5: 117.64 | H5: 790.01 | I5: 18.16 | J5: 38.37 | K5: 25.07 | L5: 25.04 | M5: 309.73 | N5: 0.21 | O5: 16905.77 | P5: 183.18 | Q5: 362.52 | R5: 249.6 | S5: 1.122 | T5: 2883.95 | U5: 249.6
B6: =B5+1 -> 4 | C6: Zydus Wellness | D6: 517 | E6: 68.37 | F6: 16448.97 | G6: -643.12 | H6: 964.9 | I6: 6.16 | J6: 44.47 | K6: 31.82 | L6: 31.82 | M6: 3042 | N6: 0.53 | O6: 19369.47 | P6: 84.8 | Q6: 383.8 | R6: 240.42 | S6: 0.706 | T6: 3389 | U6: 240
B7: =B6+1 -> 5 | C7: Gopal Snacks | D7: 333.05 | E7: 117.24 | F7: 4150.55 | G7: 190.04 | H7: 400.76 | I7: 16.31 | J7: 56.75 | K7: 12.46 | L7: 12.46 | M7: 64.92 | N7: 0.15 | O7: 4214.55 | P7: 104.32 | Q7: 108.98 | R7: 35.4 | S7: 0.76 | T7: 1416.08 | U7: 35.4
B8: =B7+1 -> 6 | C8: Hind. Unilever | D8: 2286.2 | E8: 49.19 | F8: 537163.66 | G8: 8.62 | H8: 16351 | I8: 28.42 | J8: 33.91 | K8: 234.96 | L8: 234.96 | M8: 1478 | N8: 0.03 | O8: 535393.66 | P8: 46.98 | Q8: 15790 | R8: 10927.02 | S8: 0.514 | T8: 64468 | U8: 10927.02
B9: =B8+1 -> 7 | C9: ITC | D9: 307.5 | E9: 18.79 | F9: 385281.07 | G9: 9.62 | H9: 20047.3 | I9: 36.79 | J9: 12.84 | K9: 1252.95 | L9: 1248.47 | M9: 362.97 | N9: 0.01 | O9: 381597.68 | P9: 25.44 | Q9: 28479.56 | R9: 20630 | S9: 0.572 | T9: 79808.72 | U9: 20630
B10: =B9+1 -> 8 | C10: Marico | D10: 831 | E10: 61.27 | F10: 107876.16 | G10: 13.99 | H10: 3333 | I10: 47.21 | J10: 42.63 | K10: 129.81 | L10: 129.55 | M10: 557 | N10: 0.13 | O10: 107940.16 | P10: 76.91 | Q10: 2532 | R10: 1762 | S10: 0.458 | T10: 13611 | U10: 1762
B11: =B10+1 -> 9 | C11: Patanjali Foods | D11: 459.5 | E11: 29.75 | F11: 49998.38 | G11: 68.21 | H11: 10483.71 | I11: 15.55 | J11: 25.67 | K11: 108.81 | L11: 108.6 | M11: 2895.22 | N11: 0.24 | O11: 51294.27 | P11: 113.87 | Q11: 2088.81 | R11: 1679.58 | S11: 1.14 | T11: 38718 | U11: 1679.58

Sheet Comps
A1: Britannia Industries Limited
A2: Comps Valuation
H5: Market Data | O5: Financial Data | S5: Valuation Metrics
H6: Price | I6: Shares | J6: Market Cap | K6: Debt | L6: Cash | M6: EV | O6: Sale | P6: EBITDA | Q6: Earnings | S6: EV/Sales | T6: EV/EBITDA | U6: P/E
D7: Company Name | H7: ₹/share | I7: in Cr | J7: ₹ Cr | K7: ₹ Cr | L7: ₹ Cr | M7: ₹ Cr | O7: ₹ Cr | P7: ₹ Cr | Q7: ₹ Cr | S7: x | T7: x | U7: x
D8: {='Comp Data'!C3:C11} -> Nestle India | H8: ='Comp Data'!D3 -> 1484.4 | I8: ='Comp Data'!K3 -> 192.83 | J8: =H8*I8 -> 286236.85 | K8: ='Comp Data'!M3 -> 444.16 | L8: ='Comp Data'!P3 -> 115.27 | M8: ='Comp Data'!O3 -> 285342.24 | O8: ='Comp Data'!T3 -> 23154.6 | P8: ='Comp Data'!Q3 -> 5346.41 | Q8: {='Comp Data'!U3:U11} -> 3451.73 | S8: =M8/O8 -> 12.32335 | T8: =M8/P8 -> 53.370811 | U8: =J8/Q8 -> 82.92562
D9: Britannia Inds. | H9: ='Comp Data'!D4 -> 5517.8 | I9: ='Comp Data'!K4 -> 24.09 | J9: =H9*I9 -> 132923.8 | K9: ='Comp Data'!M4 -> 1380.28 | L9: ='Comp Data'!P4 -> 60.39 | M9: ='Comp Data'!O4 -> 133934.09 | O9: ='Comp Data'!T4 -> 19151.59 | P9: ='Comp Data'!Q4 -> 3738.37 | Q9: 2537.01 | S9: =M9/O9 -> 6.9933666 | T9: =M9/P9 -> 35.826868 | U9: =J9/Q9 -> 52.393882
D10: Bikaji Foods | H10: ='Comp Data'!D5 -> 673.3 | I10: ='Comp Data'!K5 -> 25.07 | J10: =H10*I10 -> 16879.631 | K10: ='Comp Data'!M5 -> 309.73 | L10: ='Comp Data'!P5 -> 183.18 | M10: ='Comp Data'!O5 -> 16905.77 | O10: ='Comp Data'!T5 -> 2883.95 | P10: ='Comp Data'!Q5 -> 362.52 | Q10: 249.6 | S10: =M10/O10 -> 5.8620191 | T10: =M10/P10 -> 46.634034 | U10: =J10/Q10 -> 67.626727
D11: Zydus Wellness | H11: ='Comp Data'!D6 -> 517 | I11: ='Comp Data'!K6 -> 31.82 | J11: =H11*I11 -> 16450.94 | K11: ='Comp Data'!M6 -> 3042 | L11: ='Comp Data'!P6 -> 84.8 | M11: ='Comp Data'!O6 -> 19369.47 | O11: ='Comp Data'!T6 -> 3389 | P11: ='Comp Data'!Q6 -> 383.8 | Q11: 240 | S11: =M11/O11 -> 5.7153939 | T11: =M11/P11 -> 50.467613 | U11: =J11/Q11 -> 68.545583
D12: Gopal Snacks | H12: ='Comp Data'!D7 -> 333.05 | I12: ='Comp Data'!K7 -> 12.46 | J12: =H12*I12 -> 4149.803 | K12: ='Comp Data'!M7 -> 64.92 | L12: ='Comp Data'!P7 -> 104.32 | M12: ='Comp Data'!O7 -> 4214.55 | O12: ='Comp Data'!T7 -> 1416.08 | P12: ='Comp Data'!Q7 -> 108.98 | Q12: 35.4 | S12: =M12/O12 -> 2.976209 | T12: =M12/P12 -> 38.672692 | U12: =J12/Q12 -> 117.22607
D13: Hind. Unilever | H13: ='Comp Data'!D8 -> 2286.2 | I13: ='Comp Data'!K8 -> 234.96 | J13: =H13*I13 -> 537165.55 | K13: ='Comp Data'!M8 -> 1478 | L13: ='Comp Data'!P8 -> 46.98 | M13: ='Comp Data'!O8 -> 535393.66 | O13: ='Comp Data'!T8 -> 64468 | P13: ='Comp Data'!Q8 -> 15790 | Q13: 10927.02 | S13: =M13/O13 -> 8.3047971 | T13: =M13/P13 -> 33.907135 | U13: =J13/Q13 -> 49.159382
D14: ITC | H14: ='Comp Data'!D9 -> 307.5 | I14: ='Comp Data'!K9 -> 1252.95 | J14: =H14*I14 -> 385282.12 | K14: ='Comp Data'!M9 -> 362.97 | L14: ='Comp Data'!P9 -> 25.44 | M14: ='Comp Data'!O9 -> 381597.68 | O14: ='Comp Data'!T9 -> 79808.72 | P14: ='Comp Data'!Q9 -> 28479.56 | Q14: 20630 | S14: =M14/O14 -> 4.7814033 | T14: =M14/P14 -> 13.399002 | U14: =J14/Q14 -> 18.675818
D15: Marico | H15: ='Comp Data'!D10 -> 831 | I15: ='Comp Data'!K10 -> 129.81 | J15: =H15*I15 -> 107872.11 | K15: ='Comp Data'!M10 -> 557 | L15: ='Comp Data'!P10 -> 76.91 | M15: ='Comp Data'!O10 -> 107940.16 | O15: ='Comp Data'!T10 -> 13611 | P15: ='Comp Data'!Q10 -> 2532 | Q15: 1762 | S15: =M15/O15 -> 7.9303622 | T15: =M15/P15 -> 42.630395 | U15: =J15/Q15 -> 61.221402
D16: Patanjali Foods | H16: ='Comp Data'!D11 -> 459.5 | I16: ='Comp Data'!K11 -> 108.81 | J16: =H16*I16 -> 49998.195 | K16: ='Comp Data'!M11 -> 2895.22 | L16: ='Comp Data'!P11 -> 113.87 | M16: ='Comp Data'!O11 -> 51294.27 | O16: ='Comp Data'!T11 -> 38718 | P16: ='Comp Data'!Q11 -> 2088.81 | Q16: 1679.58 | S16: =M16/O16 -> 1.3248171 | T16: =M16/P16 -> 24.556695 | U16: =J16/Q16 -> 29.768272
D18: Average | S18: =AVERAGE(S8:S15) -> 6.8608627 | T18: =AVERAGE(T8:T15) -> 39.363569 | U18: =AVERAGE(U8:U15) -> 64.721811
D19: Median | S19: =MEDIAN(S8:S15) -> 6.4276929 | T19: =MEDIAN(T8:T15) -> 40.651544 | U19: =MEDIAN(U8:U15) -> 64.424064
D21: =D9 -> Britannia Inds. | H21: {=H9:M9} -> 5517.8 | I21: 24.09 | J21: 132923.8 | K21: 1380.28 | L21: 60.39 | M21: 133934.09 | O21: {=O9:Q9} -> 19151.59 | P21: 3738.37 | Q21: 2537.01 | S21: =S9 -> 6.9933666 | T21: =T9 -> 35.826868 | U21: =U9 -> 52.393882
D23: Metric | E23: Comps | H23: EV | I23: Net Debt | J23: Equity Value | K23: Shares | L23: Share Price
D24: {=TRANSPOSE(S6:U6)} -> EV/Sales | E24: {=TRANSPOSE(S18:U18)} -> 6.8608627 | H24: =E24*O21 -> 131396.43 | I24: =K21-L21 -> 1319.89 | J24: =H24-I24 -> 130076.54 | K24: =I21 -> 24.09 | L24: =J24/K24 -> 5399.6073
D25: EV/EBITDA | E25: 39.363569 | H25: =E25*P21 -> 147155.59 | I25: =I24 -> 1319.89 | J25: =H25-I25 -> 145835.7 | K25: =K24 -> 24.09 | L25: =J25/K25 -> 6053.7856
D26: P/E | E26: 64.721811 | H26: =SUM(I26:J26) -> 165519.77 | I26: =I25 -> 1319.89 | J26: =E26*Q21 -> 164199.88 | K26: =K25 -> 24.09 | L26: =J26/K26 -> 6816.1014

Sheet WACC
A1: Britannia Industries Ltd.
A2: Weigthed Average Cost of Capital
A5: Comparable Companies Beta
H6: Equity | I6: Total | J6: Debt/ | K6: Debt/ | L6: Tax | M6: Levered | N6: Unlevered
D7: Name | H7: Value | I7: Debt | J7: Equity | K7: Capital | L7: Rate% | M7: Beta | N7: Beta
D8: ='Comp Data'!C3 -> Nestle India | H8: =Comps!J8 -> 286236.85 | I8: =Comps!K8 -> 444.16 | J8: =I8/H8 -> 0.0015517219 | K8: =I8/(I8+H8) -> 0.0015493178 | L8: 0.25 | M8: ='Comp Data'!S3 -> 0.51 | N8: =M8/(J8*(1-L8)+1) -> 0.50940716
D9: ='Comp Data'!C4 -> Britannia Inds. | H9: =Comps!J9 -> 132923.8 | I9: =Comps!K9 -> 1380.28 | J9: =I9/H9 -> 0.010383994 | K9: =I9/(I9+H9) -> 0.010277275 | L9: 0.25 | M9: =Beta!I11 -> 0.4658 | N9: =M9/(J9*(1-L9)+1) -> 0.46220039
D10: ='Comp Data'!C5 -> Bikaji Foods | H10: =Comps!J10 -> 16879.631 | I10: =Comps!K10 -> 309.73 | J10: =I10/H10 -> 0.018349335 | K10: =I10/(I10+H10) -> 0.018018704 | L10: 0.25 | M10: ='Comp Data'!S5 -> 1.122 | N10: =M10/(J10*(1-L10)+1) -> 1.1067686
D11: ='Comp Data'!C6 -> Zydus Wellness | H11: =Comps!J11 -> 16450.94 | I11: =Comps!K11 -> 3042 | J11: =I11/H11 -> 0.18491345 | K11: =I11/(I11+H11) -> 0.1560565 | L11: 0.25 | M11: ='Comp Data'!S6 -> 0.706 | N11: =M11/(J11*(1-L11)+1) -> 0.62001339
D12: ='Comp Data'!C7 -> Gopal Snacks | H12: =Comps!J12 -> 4149.803 | I12: =Comps!K12 -> 64.92 | J12: =I12/H12 -> 0.015644116 | K12: =I12/(I12+H12) -> 0.015403147 | L12: 0.25 | M12: ='Comp Data'!S7 -> 0.76 | N12: =M12/(J12*(1-L12)+1) -> 0.75118627
D13: ='Comp Data'!C8 -> Hind. Unilever | H13: =Comps!J13 -> 537165.55 | I13: =Comps!K13 -> 1478 | J13: =I13/H13 -> 0.0027514795 | K13: =I13/(I13+H13) -> 0.0027439296 | L13: 0.25 | M13: ='Comp Data'!S8 -> 0.514 | N13: =M13/(J13*(1-L13)+1) -> 0.51294149
D14: ='Comp Data'!C9 -> ITC | H14: =Comps!J14 -> 385282.12 | I14: =Comps!K14 -> 362.97 | J14: =I14/H14 -> 0.00094208887 | K14: =I14/(I14+H14) -> 0.00094120217 | L14: 0.25 | M14: ='Comp Data'!S9 -> 0.572 | N14: =M14/(J14*(1-L14)+1) -> 0.57159613
D15: ='Comp Data'!C10 -> Marico | H15: =Comps!J15 -> 107872.11 | I15: =Comps!K15 -> 557 | J15: =I15/H15 -> 0.0051635219 | K15: =I15/(I15+H15) -> 0.0051369969 | L15: 0.25 | M15: ='Comp Data'!S10 -> 0.458 | N15: =M15/(J15*(1-L15)+1) -> 0.45623317
D16: ='Comp Data'!C11 -> Patanjali Foods | H16: =Comps!J16 -> 49998.195 | I16: =Comps!K16 -> 2895.22 | J16: =I16/H16 -> 0.05790649 | K16: =I16/(I16+H16) -> 0.05473687 | L16: 0.25 | M16: ='Comp Data'!S11 -> 1.14 | N16: =M16/(J16*(1-L16)+1) -> 1.0925507
D18: Average | H18: =AVERAGE(_xlfn.ANCHORARRAY(H8)) -> 286236.85 | I18: =AVERAGE(I8:I15) -> 954.8825 | J18: =AVERAGE(J8:J15) -> 0.029962463 | K18: =AVERAGE(K8:K15) -> 0.026265884 | L18: =AVERAGE(L8:L16) -> 0.25 | M18: 0.65224175 | N18: 0.54925621
D19: Median | H19: =MEDIAN(_xlfn.ANCHORARRAY(H8)) -> 286236.85 | I19: =MEDIAN(I8:I15) -> 500.58 | J19: =MEDIAN(J8:J15) -> 0.0077737581 | K19: =MEDIAN(K8:K15) -> 0.007707136 | L19: =MEDIAN(L8:L15) -> 0.25 | M19: 0.57148874 | N19: 0.48125368
D21: =A1 -> Britannia Industries Ltd. | H21: =H9 -> 132923.8 | I21: =I9 -> 1380.28 | J21: =J9 -> 0.010383994 | K21: =K9 -> 0.010277275 | L21: =L9 -> 0.25
A23: WACC Calculation
C25: Target Capital Structure
D27: Proportion of Debt | H27: =K19 -> 0.007707136
D28: Proportion Of Equity | H28: =1-H27 -> 0.99229286
C30: Current Capital Structure
D31: Market Cap | H31: =H21 -> 132923.8
D32: Total Debt | H32: =I21 -> 1380.28
D33: Debt/ Equity | H33: =J21 -> 0.010383994
C35: Cost of Debt
D36: Pre Tax Cost of Debt | H36: =Model!N12 -> 0.066492615
D37: Tax Rate | H37: =Model!N14 -> 0.25637878
D38: After Tax Cost of Debt | H38: =H36*(1-H37) -> 0.04944532
C40: Cost of Equity
D41: Risk Free Rate | H41: 0.0703
D42: Equity Market Return | H42: ='Market Data'!H9 -> 0.11358055
D43: Equity Risk Premium | H43: =H42-H41 -> 0.043280548
D44: Levered Equity Beta | H44: =N19*(1+H33*(1-H37)) -> 0.4849698
D45: Cost of Equity | H45: =H41+H43*H44 -> 0.091289759
D47: WACC | H47: =(H45*H28)+(H38*H27) -> 0.090967258

Sheet Beta
A1: Britannia Industries Limited
A2: Company Beta(Regression)
A3: Date | B3: Britannia Price | C3: Nifty Price | D3: Britannia Return | E3: Nifty Return
A4: 44333 | B4: 3223.5239 | C4: 15175.3 | D4: -0.018763694 | E4: 0.033894726
A5: 44340 | B5: 3211.9836 | C5: 15435.65 | D5: -0.003580021 | E5: 0.017156207
A6: 44347 | B6: 3285.9214 | C6: 15670.25 | D6: 0.02301934 | E6: 0.015198557
A7: 44354 | B7: 3350.5227 | C7: 15799.35 | D7: 0.019660032 | E7: 0.0082385163
A8: 44361 | B8: 3408.25 | C8: 15683.35 | D8: 0.01722934 | E8: -0.0073420744
A9: 44368 | B9: 3456.1362 | C9: 15860.35 | D9: 0.014050093 | E9: 0.011285854
A10: 44375 | B10: 3338.6572 | C10: 15722.2 | D10: -0.033991427 | E10: -0.0087103637
A11: 44382 | B11: 3273.3496 | C11: 15689.8 | D11: -0.019561043 | E11: -0.0020608051 | H11: Beta | I11: =M31 -> 0.4658
A12: 44389 | B12: 3240.4365 | C12: 15923.4 | D12: -0.010054864 | E12: 0.014888691 | H12: Rsquare | I12: =M17 -> 0.103
A13: 44396 | B13: 3239.3066 | C13: 15856.05 | D13: -0.00034868229 | E13: -0.004229661 | L13: SUMMARY OUTPUT
A14: 44403 | B14: 3223.8623 | C14: 15763.05 | D14: -0.0047677907 | E14: -0.0058652692
A15: 44410 | B15: 3393.936 | C15: 16238.2 | D15: 0.052754651 | E15: 0.030143303 | L15: Regression Statistics
A16: 44417 | B16: 3370.9111 | C16: 16529.1 | D16: -0.0067841297 | E16: 0.017914511 | L16: Multiple R | M16: 0.321
A17: 44424 | B17: 3668.8689 | C17: 16450.5 | D17: 0.088390869 | E17: -0.0047552263 | L17: R Square | M17: 0.103
A18: 44431 | B18: 3711.8113 | C18: 16705.199 | D18: 0.011704529 | E18: 0.015482765 | L18: Adjusted R Square | M18: 0.1
A19: 44438 | B19: 3883.8157 | C19: 17323.6 | D19: 0.046339747 | E19: 0.037018439 | L19: Standard Error | M19: 0.0243
A20: 44445 | B20: 3833.5278 | C20: 17369.25 | D20: -0.012948051 | E20: 0.0026351562 | L20: Observations | M20: 279
A21: 44452 | B21: 3815.6824 | C21: 17585.15 | D21: -0.0046551009 | E21: 0.012430035
A22: 44459 | B22: 3807.2537 | C22: 17853.199 | D22: -0.0022089656 | E22: 0.015242908 | L22: ANOVA
A23: 44466 | B23: 3692.5532 | C23: 17532.051 | D23: -0.030126818 | E23: -0.017988285 | M23: df | N23: SS | O23: MS | P23: F | Q23: Significance F
A24: 44473 | B24: 3656.9565 | C24: 17895.199 | D24: -0.0096401264 | E24: 0.020713403 | L24: Regression | M24: 1 | N24: 0.0188 | O24: 0.0188 | P24: 31.91 | Q24: 4.01e-08
A25: 44480 | B25: 3667.8335 | C25: 18338.551 | D25: 0.0029743184 | E25: 0.024774888 | L25: Residual | M25: 277 | N25: 0.1632 | O25: 0.000589
A26: 44487 | B26: 3474.9231 | C26: 18114.9 | D26: -0.05259519 | E26: -0.012195641 | L26: Total | M26: 278 | N26: 0.182
A27: 44494 | B27: 3461.5039 | C27: 17671.65 | D27: -0.0038617227 | E27: -0.024468807
A28: 44501 | B28: 3418.2793 | C28: 17916.801 | D28: -0.012487234 | E28: 0.013872524
A29: 44508 | B29: 3472.9927 | C29: 18102.75 | D29: 0.016006117 | E29: 0.010378483 | M29: Coefficients | N29: Standard Error | O29: t Stat | P29: P-value | Q29: Lower 95% | R29: Upper 95%
A30: 44515 | B30: 3363.4246 | C30: 17764.801 | D30: -0.031548617 | E30: -0.018668391 | L30: Intercept | M30: 0.0012 | N30: 0.002 | O30: 0.78 | P30: 0.436 | Q30: -0.002 | R30: 0.004
A31: 44522 | B31: 3348.0742 | C31: 17026.449 | D31: -0.0045639025 | E31: -0.041562614 | L31: Market Beta | M31: 0.4658 | N31: 0.082 | O31: 5.649 | P31: 0 | Q31: 0.303 | R31: 0.628
A32: 44529 | B32: 3346.615 | C32: 17196.699 | D32: -0.00043584115 | E32: 0.0099991488
A33: 44536 | B33: 3420.7278 | C33: 17511.301 | D33: 0.022145599 | E33: 0.018294299
A34: 44543 | B34: 3330.0403 | C34: 16985.199 | D34: -0.026511171 | E34: -0.030043546
A35: 44550 | B35: 3334.8904 | C35: 17003.75 | D35: 0.0014564682 | E35: 0.0010921733
A36: 44557 | B36: 3395.8196 | C36: 17354.051 | D36: 0.018270225 | E36: 0.020601384
A37: 44564 | B37: 3519.5137 | C37: 17812.699 | D37: 0.036425402 | E37: 0.026428898
A38: 44571 | B38: 3495.688 | C38: 18255.75 | D38: -0.0067695954 | E38: 0.024872748
A39: 44578 | B39: 3407.4023 | C39: 17617.15 | D39: -0.025255585 | E39: -0.034980738
A40: 44585 | B40: 3305.0852 | C40: 17101.949 | D40: -0.030027901 | E40: -0.029244297
A41: 44592 | B41: 3354.384 | C41: 17516.301 | D41: 0.014916054 | E41: 0.024228324
A42: 44599 | B42: 3277.6814 | C42: 17374.75 | D42: -0.022866385 | E42: -0.0080810888
A43: 44606 | B43: 3278.7173 | C43: 17276.301 | D43: 0.00031604313 | E43: -0.0056662236
... A263: 46146 | B263: 5520 | C263: 24176.15 | D263: -0.035976249 | E263: 0.0074424099

Sheet Market Data
A1: Britannia Industries Limited
A2: Market Return
A3: Date | B3: Britannia Price | C3: Nifty Price | D3: Britannia Return | E3: Nifty Return
A4: 44333 | B4: 3223.5239 | C4: 15175.3 | D4: -0.018763694 | E4: 0.033894726
A5: 44340 | B5: 3211.9836 | C5: 15435.65 | D5: -0.003580021 | E5: 0.017156207
A6: 44347 | B6: 3285.9214 | C6: 15670.25 | D6: 0.02301934 | E6: 0.015198557
A7: 44354 | B7: 3350.5227 | C7: 15799.35 | D7: 0.019660032 | E7: 0.0082385163 | G7: No. of Years | H7: 5
A8: 44361 | B8: 3408.25 | C8: 15683.35 | D8: 0.01722934 | E8: -0.0073420744 | G8: Index | H8: Nifty 50
A9: 44368 | B9: 3456.1362 | C9: 15860.35 | D9: 0.014050093 | E9: 0.011285854 | G9: Market Return | H9: =_xlfn.RRI(H7,B4,B263) -> 0.11358055
A10: 44375 | B10: 3338.6572 | C10: 15722.2 | D10: -0.033991427 | E10: -0.0087103637 | G10: Levered Beta | H10: =SLOPE(D4:D263,E4:E263) -> 0.52392004
A11: 44382 | B11: 3273.3496 | C11: 15689.8 | D11: -0.019561043 | E11: -0.0020608051
A12: 44389 | B12: 3240.4365 | C12: 15923.4 | D12: -0.010054864 | E12: 0.014888691
A13: 44396 | B13: 3239.3066 | C13: 15856.05 | D13: -0.00034868229 | E13: -0.004229661
A14: 44403 | B14: 3223.8623 | C14: 15763.05 | D14: -0.0047677907 | E14: -0.0058652692
A15: 44410 | B15: 3393.936 | C15: 16238.2 | D15: 0.052754651 | E15: 0.030143303
A16: 44417 | B16: 3370.9111 | C16: 16529.1 | D16: -0.0067841297 | E16: 0.017914511
A17: 44424 | B17: 3668.8689 | C17: 16450.5 | D17: 0.088390869 | E17: -0.0047552263
A18: 44431 | B18: 3711.8113 | C18: 16705.199 | D18: 0.011704529 | E18: 0.015482765
A19: 44438 | B19: 3883.8157 | C19: 17323.6 | D19: 0.046339747 | E19: 0.037018439
A20: 44445 | B20: 3833.5278 | C20: 17369.25 | D20: -0.012948051 | E20: 0.0026351562
A21: 44452 | B21: 3815.6824 | C21: 17585.15 | D21: -0.0046551009 | E21: 0.012430035
A22: 44459 | B22: 3807.2537 | C22: 17853.199 | D22: -0.0022089656 | E22: 0.015242908
... A263: 46146 | B263: 5520 | C263: 24176.15 | D263: -0.035976249 | E263: 0.0074424099
